img_masker/__init__.py
img_masker/masker.py
img_masker-1.0.2.dist-info/licenses/LICENSE
img_masker-1.0.2.dist-info/METADATA
img_masker-1.0.2.dist-info/WHEEL
img_masker-1.0.2.dist-info/top_level.txt
img_masker-1.0.2.dist-info/RECORD
