Metadata-Version: 2.4
Name: img-masker
Version: 1.0.2
Summary: A simple image masking tool.
Author: j-ncel
Project-URL: Homepage, https://github.com/j-ncel/img-masker
Project-URL: Repository, https://github.com/j-ncel/img-masker
Keywords: image processing,masking,Python
Classifier: Programming Language :: Python :: 3
Classifier: Operating System :: OS Independent
Requires-Python: >=3.8
License-File: LICENSE
Requires-Dist: Pillow
Requires-Dist: requests
Dynamic: license-file
